grammatica/__init__.py
grammatica/_version.py
grammatica/constants.py
grammatica/utils.py
grammatica/grammar/__init__.py
grammatica/grammar/base.py
grammatica/grammar/char_range.py
grammatica/grammar/derivation_rule.py
grammatica/grammar/string.py
grammatica/grammar/group/__init__.py
grammatica/grammar/group/and_.py
grammatica/grammar/group/base.py
grammatica/grammar/group/or_.py
grammatica-0.2.0.dist-info/METADATA
grammatica-0.2.0.dist-info/WHEEL
grammatica-0.2.0.dist-info/licenses/LICENSE
grammatica-0.2.0.dist-info/RECORD
