Metadata-Version: 2.4
Name: grammatica
Version: 0.2.0
Summary: Grammatica is a GBNF (GGML BNF) grammar builder that exposes the full richness of the GBNF notation system using a syntax that reflects the resulting grammar.
Project-URL: homepage, https://pypi.org/project/grammatica/
Project-URL: documentation, https://londowski.com/docs/grammatica/stable/
Project-URL: repository, https://github.com/yaphott/grammatica
Project-URL: changelog, https://github.com/yaphott/grammatica/blob/main/CHANGELOG.md
Project-URL: issues, https://github.com/yaphott/grammatica/issues
Author-email: Nicholas Londowski <londowski@proton.me>
License:                                  Apache License
License-File: LICENSE
Keywords: bnf,gbnf,ggml,grammar,grammatica,llm,prompt,regex,system
Classifier: Development Status :: 3 - Alpha
Classifier: Intended Audience :: Developers
Classifier: License :: OSI Approved :: Apache Software License
Classifier: Natural Language :: English
Classifier: Operating System :: OS Independent
Classifier: Programming Language :: Python
Classifier: Programming Language :: Python :: 3
Classifier: Programming Language :: Python :: 3 :: Only
Classifier: Programming Language :: Python :: 3.10
Classifier: Programming Language :: Python :: 3.11
Classifier: Programming Language :: Python :: 3.12
Classifier: Programming Language :: Python :: 3.13
Classifier: Programming Language :: Python :: 3.14
Classifier: Topic :: Software Development
Classifier: Topic :: Software Development :: Libraries
Classifier: Topic :: Software Development :: Libraries :: Python Modules
Classifier: Topic :: Utilities
Requires-Python: <4,>=3.10
Requires-Dist: typing-extensions>=4.5.0; python_version < '3.12'
Provides-Extra: dev
Requires-Dist: black>=22.10.0; extra == 'dev'
Requires-Dist: isort>=5.2.1; extra == 'dev'
Requires-Dist: mypy>=1.0; extra == 'dev'
Requires-Dist: pylint>=3.0.0; extra == 'dev'
Provides-Extra: doc
Requires-Dist: pydata-sphinx-theme==0.16.1; extra == 'doc'
Requires-Dist: sphinx-autodoc-typehints==3.1.0; extra == 'doc'
Requires-Dist: sphinx==8.2.3; extra == 'doc'
Provides-Extra: test
Requires-Dist: pytest-cov>=6.0.0; extra == 'test'
Requires-Dist: pytest>=7.0.0; extra == 'test'
